image_processing/__init__.py
image_processing/processing/__init__.py
image_processing/processing/combination.py
image_processing/processing/transformation.py
image_processing/utils/__init__.py
image_processing/utils/io.py
image_processing/utils/plot.py
chavatte_image_processing-0.1.0.dist-info/METADATA
chavatte_image_processing-0.1.0.dist-info/WHEEL
chavatte_image_processing-0.1.0.dist-info/top_level.txt
chavatte_image_processing-0.1.0.dist-info/RECORD
