Metadata-Version: 2.2
Name: chavatte_image_processing
Version: 0.1.0
Summary: Biblioteca para processamento de imagens
Home-page: https://github.com/chavatte/LAB-SUZANO-PYTHON-DEVELOPER/blob/main/projects/LAB-04/README.md
Author: João Carlos Chavatte
Author-email: chavatte@duck.com
Classifier: Development Status :: 3 - Alpha
Classifier: Intended Audience :: Developers
Classifier: License :: OSI Approved :: MIT License
Classifier: Topic :: Scientific/Engineering :: Image Processing
Requires-Python: >=3.8
Dynamic: author
Dynamic: author-email
Dynamic: classifier
Dynamic: description
Dynamic: description-content-type
Dynamic: home-page
Dynamic: requires-python
Dynamic: summary
